MANIFEST.in
README.rst
setup.py
scripts/wfm
wfm/__init__.py
wfm.egg-info/PKG-INFO
wfm.egg-info/SOURCES.txt
wfm.egg-info/dependency_links.txt
wfm.egg-info/pbr.json
wfm.egg-info/requires.txt
wfm.egg-info/top_level.txt