Metadata-Version: 1.1
Name: wfm
Version: 0.1.2
Summary: A command-line interface for adding to your WorkflowMax timesheet.
Home-page: https://github.com/rkhleics/wfm
Author: colons
Author-email: pypi@colons.co
License: BSD
Platform: any
Classifier: Development Status :: 3 - Alpha
Classifier: License :: OSI Approved :: BSD License
Classifier: Operating System :: OS Independent
